mccq/__init__.py
mccq/__main__.py
mccq/argument_parser.py
mccq/errors.py
mccq/query_arguments.py
mccq/query_manager.py
mccq/typedefs.py
mccq/version_database.py
mccq/cli/__init__.py
mccq/cli/cli.py
mccq/cli/completer.py
mccq/cli/loop.py
mccq/cli/meta.py
mccq/data_loader/__init__.py
mccq/data_loader/filesystem_data_loader.py
mccq/data_loader/internet_data_loader.py
mccq/data_loader/abc/__init__.py
mccq/data_loader/abc/data_loader.py
mccq/data_parser/__init__.py
mccq/data_parser/v1_data_parser.py
mccq/data_parser/abc/__init__.py
mccq/data_parser/abc/data_parser.py
mccq/node/__init__.py
mccq/node/data_node.py
mccq/node/query_node.py
mccq/node/abc/__init__.py
mccq/node/abc/node.py
mccq-1.0.2.dist-info/METADATA
mccq-1.0.2.dist-info/RECORD
mccq-1.0.2.dist-info/WHEEL
mccq-1.0.2.dist-info/top_level.txt
