Metadata-Version: 2.1
Name: mccq
Version: 1.0.2
Summary: Minecraft command query program. Inspired by the in-game help command, with added features like multiple version support and expandable regex search.
Home-page: https://github.com/Arcensoth/mccq
Author: Arcensoth
Author-email: arcensoth@gmail.com
License: MIT
Keywords: minecraft command query help utility
Platform: UNKNOWN
Classifier: Programming Language :: Python :: 3.6
Classifier: License :: OSI Approved :: MIT License
Classifier: Operating System :: OS Independent
Classifier: Development Status :: 5 - Production/Stable
Requires-Python: >=3.6
